LICENSE
README.md
setup.py
CVE_2023_29489.egg-info/PKG-INFO
CVE_2023_29489.egg-info/SOURCES.txt
CVE_2023_29489.egg-info/dependency_links.txt
CVE_2023_29489.egg-info/entry_points.txt
CVE_2023_29489.egg-info/requires.txt
CVE_2023_29489.egg-info/top_level.txt
cve202329489/__init__.py
cve202329489/main.py
cve202329489/includes/__init__.py
cve202329489/includes/bot.py
cve202329489/includes/filereader.py
cve202329489/includes/scan.py
cve202329489/includes/writefile.py
cve202329489/utils/__init__.py
cve202329489/utils/configure.py
cve202329489/utils/const.py
cve202329489/utils/helpers.py
cve202329489/utils/status.py